count_views.py
flickr_views_counter-0.1.0.dist-info/DESCRIPTION.rst
flickr_views_counter-0.1.0.dist-info/entry_points.txt
flickr_views_counter-0.1.0.dist-info/METADATA
flickr_views_counter-0.1.0.dist-info/metadata.json
flickr_views_counter-0.1.0.dist-info/namespace_packages.txt
flickr_views_counter-0.1.0.dist-info/RECORD
flickr_views_counter-0.1.0.dist-info/top_level.txt
flickr_views_counter-0.1.0.dist-info/WHEEL
