Metadata-Version: 2.0
Name: flickr-views-counter
Version: 0.1.0
Summary: Get view counts, favorites, and other data for each picture in a user's photostream
Home-page: https://github.com/jordanjoz1/flickr-views-counter
Author: Jordan Jozwiak
Author-email: support@jozapps.com
License: MIT
Keywords: flickr photos views favorites
Platform: UNKNOWN
Classifier: License :: OSI Approved :: BSD License
Classifier: Intended Audience :: Developers
Classifier: Programming Language :: Python
Requires-Dist: flickrapi
